htmx_components_python/__init__.py
htmx_components_python-0.0.2.dist-info/LICENSE
htmx_components_python-0.0.2.dist-info/METADATA
htmx_components_python-0.0.2.dist-info/WHEEL
htmx_components_python-0.0.2.dist-info/top_level.txt
htmx_components_python-0.0.2.dist-info/RECORD
