Metadata-Version: 2.1
Name: htmx-components-python
Version: 0.0.2
Summary: HTMX Components common util for Python
Author: Neil McGuigan
Project-URL: Homepage, https://github.com/neilmcguigan/htmx-components-python
License-File: LICENSE
